README
setup.cfg
setup.py
Protea.egg-info/PKG-INFO
Protea.egg-info/SOURCES.txt
Protea.egg-info/dependency_links.txt
Protea.egg-info/top_level.txt
protea/__init__.py
protea/exceptions.py