Metadata-Version: 1.1
Name: Protea
Version: 0.1a
Summary: Ashly digital audio products RS-232 interface library
Home-page: https://github.com/sebleblanc/python-protea/
Author: Sébastien Leblanc
Author-email: seb@sebleblanc.net
License: MIT
Keywords: ashly protea ne24.24M 4.24C matrix processor interface rs-232
Platform: UNKNOWN
Classifier: Development Status :: 3 - Alpha
Classifier: Intended Audience :: Developers
Classifier: Intended Audience :: System Administrators
Classifier: Intended Audience :: Telecommunications Industry
Classifier: Topic :: Multimedia :: Sound/Audio
Classifier: Topic :: Terminals :: Serial
Classifier: Topic :: System :: Hardware :: Hardware Drivers
Classifier: Topic :: Utilities
Classifier: Programming Language :: Python
Classifier: Programming Language :: Python :: 2
Classifier: Programming Language :: Python :: 3
Classifier: License :: OSI Approved :: MIT License
Classifier: Operating System :: POSIX :: Linux
Classifier: Operating System :: Microsoft :: Windows
